pycheckwatt/__init__.py
pycheckwatt/const.py
pycheckwatt-0.2.11.dist-info/LICENSE
pycheckwatt-0.2.11.dist-info/METADATA
pycheckwatt-0.2.11.dist-info/WHEEL
pycheckwatt-0.2.11.dist-info/RECORD
