Metadata-Version: 2.3
Name: pycheckwatt
Version: 0.2.11
Summary: Read data from CheckWatts EnergyInBalance WEB API
License: MIT
Keywords: checkwatt,eib,battery
Author: Marcus Karlsson
Author-email: macke.karlsson@gmail.com
Requires-Python: >=3.10,<3.13
Classifier: Development Status :: 4 - Beta
Classifier: Intended Audience :: Developers
Classifier: License :: OSI Approved :: MIT License
Classifier: Programming Language :: Python :: 3
Classifier: Programming Language :: Python :: 3.10
Classifier: Programming Language :: Python :: 3.11
Classifier: Programming Language :: Python :: 3.12
Requires-Dist: aiohttp (>=3.9.1,<4.0.0)
Requires-Dist: python-dateutil (>=2.8.2,<3.0.0)
